MANIFEST.in
setup.py
imgs/__init__.py
imgs/imgs.py
visual_layer/__init__.py
visual_layer/vulcan_colab.py
vulcan_colab.egg-info/PKG-INFO
vulcan_colab.egg-info/SOURCES.txt
vulcan_colab.egg-info/dependency_links.txt
vulcan_colab.egg-info/top_level.txt