Metadata-Version: 2.1
Name: vulcan-colab
Version: 0.3.0
Summary: Vulcan Colab
Home-page: https://codigos.ufsc.br/100000000394729/colabvisuallayer
Author: Augusto Franz
Author-email: gutofranz@gmail.com
License: UNKNOWN
Platform: UNKNOWN
